LICENSE
README.md
setup.py
vibecheck/__init__.py
vibecheck.egg-info/PKG-INFO
vibecheck.egg-info/SOURCES.txt
vibecheck.egg-info/dependency_links.txt
vibecheck.egg-info/requires.txt
vibecheck.egg-info/top_level.txt