Metadata-Version: 2.1
Name: vibecheck
Version: 0.0.5
Summary: vibecheck is a Python library for getting hyperlocal feedback from notebook users.
Home-page: https://github.com/KordingLab/vibecheck/tarball/0.0.5
Author: Jordan Matelsky
Author-email: opensource@matelsky.com
License: Apache 2.0
Keywords: datatops,serverless,jupyter,notebook
License-File: LICENSE
